{"noMoreComments": false, "cursorEnd": 20, "id": "8983176", "comments": [{"postBy": {"location": "Kaohsiung City\u00b7Taiwan", "utc": 1531428900000, "level": 0, "avatar": "http://filestoresg1.beetalkmobile.com:8081/file/7982680918526260274", "name": "\u7d39\u5f64"}, "content": "\u7fa8\u6155-/-", "urls": [], "replies": {"first": [], "last": [], "noMoreReplies": true}, "images": [], "id": 92225793}, {"postBy": {"location": "", "utc": 1531495923000, "level": 0, "avatar": "http://filestoresg1.beetalkmobile.com:8081/file/7149452336260882817", "name": "\ud83c\udfa4\u2728\u5927\u5f65\ud83d\udd1e"}, "content": "\u60f3\u8a8d\u8b58p\u670b\u53cb\u02c7\ud83d\ude06\ud83d\ude06\ud83d\ude06", "urls": [], "replies": {"first": [], "last": [], "noMoreReplies": true}, "images": [], "id": 92277323}, {"postBy": {"location": "\u53f0\u5357\u5e02\u00b7\u53f0\u7063", "utc": 1531496812000, "level": 0, "avatar": "http://filestoresg1.beetalkmobile.com:8081/file/-4550963279671145662", "name": "\u311a\u529b(\uffe33\uffe3)"}, "content": "T\ud83d\ude4b\ud83d\ude4b\ud83d\ude4b", "urls": [], "replies": {"first": [], "last": [], "noMoreReplies": true}, "images": [], "id": 92278360}, {"postBy": {"location": "\u53f0\u7063", "utc": 1531581694000, "level": 0, "avatar": "http://filestoresg1.beetalkmobile.com:8081/file/-9033467667584311245", "name": "\u5f6d\u5f6d"}, "content": "++", "urls": [], "replies": {"first": [], "last": [], "noMoreReplies": true}, "images": [], "id": 92344105}, {"postBy": {"location": "", "utc": 1531583418000, "level": 0, "avatar": "http://filestoresg1.beetalkmobile.com:8081/file/-5532693007698689023", "name": "517"}, "content": "\ud83e\udd17\ud83e\udd17\ud83e\udd17", "urls": [], "replies": {"first": [{"content": "\ud83d\ude0a", "reply": "", "id": 58273574, "name": "\u599e\ud83d\udc8b"}], "last": [], "noMoreReplies": true}, "images": [], "id": 92346111}, {"postBy": {"location": "\u53f0\u5317\u5e02\u00b7\u53f0\u7063", "utc": 1531630481000, "level": 0, "avatar": "http://filestoresg1.beetalkmobile.com:8081/file/5750974679290242333", "name": "\u5c0f\u85cd\ud83d\udc4b"}, "content": "\u55e8\ud83d\udc4b", "urls": [], "replies": {"first": [{"content": "\ud83d\ude01", "reply": "", "id": 58273578, "name": "\u599e\ud83d\udc8b"}, {"content": "\u4f60\u597d\u554a\uff0c\u4ea4\u500b\u670b\u53cb", "reply": "", "id": 58298524, "name": "\u5c0f\u85cd\ud83d\udc4b"}], "last": [], "noMoreReplies": true}, "images": [], "id": 92379770}, {"postBy": {"location": "\u65b0\u5317\u5e02\u00b7\u53f0\u7063", "utc": 1531632133000, "level": 0, "avatar": "http://filestoresg1.beetalkmobile.com:8081/file/1815576283384859649", "name": "\u9cf3\u68a8"}, "content": "\u54c8\u56c9", "urls": [], "replies": {"first": [], "last": [], "noMoreReplies": true}, "images": [], "id": 92381243}, {"postBy": {"location": "\u9ad8\u96c4\u5e02\u00b7\u53f0\u7063", "utc": 1531761479000, "level": 0, "avatar": "http://filestoresg1.beetalkmobile.com:8081/file/-2432041649460711679", "name": "\u6771\u967dSun"}, "content": "\u597d \u7d66\u4f60\u8a8d\u8b58", "urls": [], "replies": {"first": [{"content": "\u4f86\ud83d\ude0f", "reply": "", "id": 58273583, "name": "\u599e\ud83d\udc8b"}], "last": [], "noMoreReplies": true}, "images": [], "id": 92491600}, {"postBy": {"location": "\u53f0\u4e2d\u5e02\u00b7\u53f0\u7063", "utc": 1531797154000, "level": 0, "avatar": "http://filestoresg1.beetalkmobile.com:8081/file/-6164036982856461824", "name": "\u672a\u4f86\u7537\u670b\u53cb\ud83d\ude08\ud83d\ude08"}, "content": "\u5b89\u5b89", "urls": [], "replies": {"first": [{"content": "\ud83d\ude0a", "reply": "", "id": 58273636, "name": "\u599e\ud83d\udc8b"}], "last": [], "noMoreReplies": true}, "images": [], "id": 92513554}, {"postBy": {"location": "\u65b0\u5317\u5e02\u00b7\u53f0\u7063", "utc": 1531798756000, "level": 0, "avatar": "http://filestoresg1.beetalkmobile.com:8081/file/-5587600443424437290", "name": "\ud83d\udc3b\u6ce1\u6cab&\u51e1\u5875\ud83d\udc3b"}, "content": "perter1314", "urls": [], "replies": {"first": [], "last": [], "noMoreReplies": true}, "images": [], "id": 92515040}, {"postBy": {"location": "\u53f0\u7063", "utc": 1531968863000, "level": 0, "avatar": "http://filestoresg1.beetalkmobile.com:8081/file/5756598703315721476", "name": "\u5f88\u611b\u7b11"}, "content": "\u4f86\ud83d\ude4c", "urls": [], "replies": {"first": [{"content": "\u4f86\ud83d\ude01", "reply": "", "id": 58273641, "name": "\u599e\ud83d\udc8b"}, {"content": "\u52a0\u597d\u53cb\u54e9\ud83d\ude02", "reply": "", "id": 58292625, "name": "\u5f88\u611b\u7b11"}], "last": [], "noMoreReplies": true}, "images": [], "id": 92655931}, {"postBy": {"location": "\u65b0\u5317\u5e02\u00b7\u53f0\u7063", "utc": 1531969587000, "level": 0, "avatar": "http://filestoresg1.beetalkmobile.com:8081/file/-6569630353558112622", "name": "\u8c93\u4ed9\u4eba"}, "content": "\u5176\u5be6\u53ea\u8981\u6b63\u5e38\u4eba\u771f\u5fc3\u60f3\u8981\u4ea4\u670b\u53cb\u7684 \u4e0d\u7ba1\u7537\u5973\u90fd\u597d\u5427", "urls": [], "replies": {"first": [], "last": [], "noMoreReplies": true}, "images": [], "id": 92656505}, {"postBy": {"location": "\u53f0\u5357\u5e02\u00b7\u53f0\u7063", "utc": 1531983641000, "level": 0, "avatar": "http://filestoresg1.beetalkmobile.com:8081/file/-7253415534504475900", "name": "\ud83c\udf08\u71c8\u6ce1"}, "content": "\u4f60\u597d\uff5e\uff5e\uff5e\uff5e", "urls": [], "replies": {"first": [{"content": "\u4f60\u597d\u554a\uff01", "reply": "", "id": 58273644, "name": "\u599e\ud83d\udc8b"}, {"content": "\u662f\u591c\u8c93\u5b50 \u9084\u662f\u65e9\u8d77\u7684\u5c0f\u59d0\u59d0\u5462\ud83d\ude02\ud83d\ude02", "reply": "\u599e\ud83d\udc8b", "id": 58283107, "name": "\ud83c\udf08\u71c8\u6ce1"}], "last": [], "noMoreReplies": true}, "images": [], "id": 92667807}, {"postBy": {"location": "", "utc": 1531991215000, "level": 0, "avatar": "http://filestoresg1.beetalkmobile.com:8081/file/-8003499045899832600", "name": "\u9b5a\u9b5a"}, "content": "\u54c8\u56c9", "urls": [], "replies": {"first": [], "last": [], "noMoreReplies": true}, "images": [], "id": 92673846}, {"postBy": {"location": "\u6843\u5712\u5e02\u00b7\u53f0\u7063", "utc": 1532158655000, "level": 0, "avatar": "http://filestoresg1.beetalkmobile.com:8081/file/1", "name": "\u674e\u5c0f\u9f8d"}, "content": "\u5b89\u5b89\u5b89", "urls": [], "replies": {"first": [], "last": [], "noMoreReplies": true}, "images": [], "id": 92807096}, {"postBy": {"location": "\u65b0\u5317\u5e02\u00b7\u53f0\u7063", "utc": 1532239532000, "level": 0, "avatar": "http://filestoresg1.beetalkmobile.com:8081/file/-2655605351951286130", "name": "Lin~\u5feb\u4f86\u966a\u6211\u904b\u52d5"}, "content": "\u4e0d\u932f", "urls": [], "replies": {"first": [], "last": [], "noMoreReplies": true}, "images": [], "id": 92876164}, {"postBy": {"location": "\u6843\u5712\u5e02\u00b7\u53f0\u7063", "utc": 1532311806000, "level": 0, "avatar": "http://filestoresg1.beetalkmobile.com:8081/file/-7998430296361124498", "name": "\u99ac\u514b"}, "content": "\u6211\u5011\u53ef\u4ee5\u4e92\u76f8\u8a8d\u8b58\uff01", "urls": [], "replies": {"first": [], "last": [], "noMoreReplies": true}, "images": [], "id": 92937071}, {"postBy": {"location": "\u53f0\u7063", "utc": 1532363031000, "level": 0, "avatar": "http://filestoresg1.beetalkmobile.com:8081/file/6013127941625586700", "name": "\u5c0f\u5180"}, "content": "\u6211\u53eb\u5c0f\u5180\u3110\u3127\u02cb<br /><br />\u4f4f\u65b0\u7af9\u5e02\u4f60\u6703\u898b\u7db2\u53cb\u55ce?<br /><br />\u6211\u53ef\u4ee5\u8ddf\u4f60\u7576\u73fe\u5be6\u751f\u6d3b\u4e2d\u7684\u670b\u53cb\u55ce?<br /><br />\u5c31\u662f\u53ef\u4ee5\u898b\u9762\u770b\u96fb\u5f71\u5531\u6b4c\u901b\u8857\u7684\u90a3\u7a2e~~~~~<br /><br />\u7576\u7136\u6211\u8acb\u5ba2\u56c9<br /><br />\u6709\u6c92\u6709\u9023\u7d61\u65b9\u5f0f\u53ef\u4ee5\u9023\u7d61\u5462?\u96fb\u8a71\u81c9\u66f8\u8cf4\u7dad\u4fe1?", "urls": [], "replies": {"first": [], "last": [], "noMoreReplies": true}, "images": [], "id": 92985289}, {"postBy": {"location": "\u53f0\u5317\u5e02\u00b7\u53f0\u7063", "utc": 1533697699000, "level": 0, "avatar": "http://filestoresg1.beetalkmobile.com:8081/file/5787505969017648898", "name": "dream"}, "content": "\u4f60\u597d", "urls": [], "replies": {"first": [], "last": [], "noMoreReplies": true}, "images": [], "id": 94090142}]}
