{"noMoreComments": true, "cursorEnd": 0, "id": "8174665", "comments": [{"postBy": {"location": "\u53f0\u4e2d\u5e02\u00b7\u53f0\u7063", "utc": 1525928777000, "level": 0, "avatar": "http://filestoresg1.beetalkmobile.com:8081/file/6819559250723034464", "name": "\u5a01\u5ec9q\u8d77\u4f86"}, "content": "\u505a\u8b8a\u6027\u55ce\uff1f", "urls": [], "replies": {"first": [], "last": [], "noMoreReplies": true}, "images": [], "id": 87785773}, {"postBy": {"location": "", "utc": 1525946892000, "level": 0, "avatar": "http://filestoresg1.beetalkmobile.com:8081/file/-4914605062254127360", "name": "\u9673\u5955"}, "content": "\u8cb7\u591a\u9ede\u597d\u311a", "urls": [], "replies": {"first": [], "last": [], "noMoreReplies": true}, "images": [], "id": 87800594}, {"postBy": {"location": "\u53f0\u7063", "utc": 1526190397000, "level": 0, "avatar": "http://filestoresg1.beetalkmobile.com:8081/file/7271051718619423187", "name": "\u6ef4\u6c34"}, "content": "\u864e\u7259\u55ce", "urls": [], "replies": {"first": [], "last": [], "noMoreReplies": true}, "images": [], "id": 88009941}]}
