{"noMoreComments": true, "cursorEnd": 0, "id": "8672773", "comments": [{"postBy": {"location": "\u65b0\u5317\u5e02\u00b7\u53f0\u7063", "utc": 1528253639000, "level": 0, "avatar": "http://filestoresg1.beetalkmobile.com:8081/file/-4088154631420570614", "name": "Ling"}, "content": "\u523a\u523a\u6b38\ud83d\ude0d", "urls": [], "replies": {"first": [], "last": [], "noMoreReplies": true}, "images": [], "id": 89687359}, {"postBy": {"location": "\u53f0\u5357\u5e02\u00b7\u53f0\u7063", "utc": 1528255351000, "level": 0, "avatar": "http://filestoresg1.beetalkmobile.com:8081/file/8107780075564523797", "name": "\ud83d\udc39\u966a\u80a5\u9f20\u6253\u724c60/20\ud83d\udc39"}, "content": "\u6211\u5bb6\u4e5f\u6709\u5927\u8001\u9f20\ud83d\ude18\ud83d\ude18\ud83d\ude18", "urls": [], "replies": {"first": [], "last": [], "noMoreReplies": true}, "images": ["http://filestoresg1.beetalkmobile.com:8081/file/2ccc45e97d7f245de9db4ab3599f4930"], "id": 89688600}]}
