{"noMoreComments": true, "cursorEnd": 0, "id": "8753013", "comments": [{"postBy": {"location": "\u6843\u5712\u5e02\u00b7\u53f0\u7063", "utc": 1529140814000, "level": 0, "avatar": "http://filestoresg1.beetalkmobile.com:8081/file/6408931240137764735", "name": "\u522a"}, "content": "+\u5716", "urls": [], "replies": {"first": [], "last": [], "noMoreReplies": true}, "images": ["http://filestoresg1.beetalkmobile.com:8081/file/cf8d60a6399fb6436864b15a96058cad", "http://filestoresg1.beetalkmobile.com:8081/file/15d45c635a2694f2786c16d9b08a1e02", "http://filestoresg1.beetalkmobile.com:8081/file/6d4303d3bf696db9e66b53a4b1c77677", "http://filestoresg1.beetalkmobile.com:8081/file/d1e24ba88ee3971d880896ea3b4b24a1", "http://filestoresg1.beetalkmobile.com:8081/file/68d229052b7a7b76df4f1daa2d620358", "http://filestoresg1.beetalkmobile.com:8081/file/05e0a83387e2d98d71a55c5e80c86f05"], "id": 90332452}]}
