{"noMoreComments": true, "cursorEnd": 0, "id": "8975402", "comments": [{"postBy": {"location": "\u65b0\u5317\u5e02\u00b7\u53f0\u7063", "utc": 1531533073000, "level": 0, "avatar": "http://filestoresg1.beetalkmobile.com:8081/file/-4080869267045253412", "name": "\u91d1\u675c\u862d"}, "content": "\u4f60\u4ee5\u70ba\u6050\u9f8d\u7d55\u8de1\u4e86\u55ce\uff1f\u4e0d\uff0c\u4f60\u932f\u4e86\uff0c\u4e0d\u7136\u6cd5\u9662\u600e\u9ebc\u6709\u4f8f\u5138\u7d00xd!", "urls": [], "replies": {"first": [], "last": [], "noMoreReplies": true}, "images": [], "id": 92302595}]}
