{"noMoreComments": true, "cursorEnd": 0, "id": "8047391", "comments": [{"postBy": {"location": "\u53f0\u7063", "utc": 1522116546000, "level": 0, "avatar": "http://filestoresg1.beetalkmobile.com:8081/file/1359463681222278900", "name": "1360"}, "content": "\u9060\u65b9\u7684\u670b\u53cb\u5728\u9019\u88e1", "urls": [], "replies": {"first": [], "last": [], "noMoreReplies": true}, "images": [], "id": 84581481}, {"postBy": {"location": "\u53f0\u7063", "utc": 1522145841000, "level": 0, "avatar": "http://filestoresg1.beetalkmobile.com:8081/file/5046887018479237204", "name": "\u8cd3\u4ed4"}, "content": "\u54c8\u56c9", "urls": [], "replies": {"first": [], "last": [], "noMoreReplies": true}, "images": [], "id": 84606142}]}
