{"noMoreComments": true, "cursorEnd": 0, "id": "8664251", "comments": [{"postBy": {"location": "\u65b0\u5317\u5e02\u00b7\u53f0\u7063", "utc": 1528160468000, "level": 0, "avatar": "http://filestoresg1.beetalkmobile.com:8081/file/5943183614516575275", "name": "\u7d05\u7334"}, "content": "\u8d77\u4e69\uff1f", "urls": [], "replies": {"first": [{"content": "\u56e0\u70ba\u6211\u5feb\u7761\u8457\u4e86", "reply": "", "id": 56963930, "name": "\u91d1\u864e\ud83d\udc2f"}], "last": [], "noMoreReplies": true}, "images": [], "id": 89616344}]}
