{"noMoreComments": true, "cursorEnd": 0, "id": "8713564", "comments": [{"postBy": {"location": "\u65b0\u5317\u5e02\u00b7\u53f0\u7063", "utc": 1528687335000, "level": 0, "avatar": "http://filestoresg1.beetalkmobile.com:8081/file/1484523217553464882", "name": "0210"}, "content": "\u52a0\u6cb9", "urls": [], "replies": {"first": [{"content": "Thk\u263a\ufe0f", "reply": "", "id": 60032570, "name": "\u6efe\u5152\ud83d\udd05"}], "last": [], "noMoreReplies": true}, "images": [], "id": 90022189}, {"postBy": {"location": "", "utc": 1528690504000, "level": 0, "avatar": "http://filestoresg1.beetalkmobile.com:8081/file/-3721681929551873809", "name": "kai"}, "content": "\u62cd\u80a9\uff01", "urls": [], "replies": {"first": [{"content": "\u263a\ufe0f", "reply": "", "id": 60032572, "name": "\u6efe\u5152\ud83d\udd05"}], "last": [], "noMoreReplies": true}, "images": [], "id": 90024358}, {"postBy": {"location": "\u53f0\u5317\u5e02\u00b7\u53f0\u7063", "utc": 1529102018000, "level": 0, "avatar": "http://filestoresg1.beetalkmobile.com:8081/file/-4341537109642998013", "name": "smith"}, "content": "\u5fc3\u7d2f\u52a0\u4e00\u4f46\u4f60\u4e5f\u592a\u6158\u4e86\u5427\uff5e\u5e6b\u82e6\u54ed\u54ed\ud83d\ude2b\ud83d\ude2b", "urls": [], "replies": {"first": [{"content": "\u54ed\u4e5f\u6c92\u7528 \u8981\u9762\u5c0d\u9084\u662f\u5f97\u9762\u5c0d\ud83e\udd23", "reply": "", "id": 60032573, "name": "\u6efe\u5152\ud83d\udd05"}, {"content": "\u52a0\u6cb9~\u4e00\u5207\u6703\u66f4\u597d\u7684\ud83d\ude02\ud83d\ude02", "reply": "", "id": 60037652, "name": "smith"}], "last": [], "noMoreReplies": true}, "images": [], "id": 90306356}, {"postBy": {"location": "\u53f0\u4e2d\u5e02\u00b7\u53f0\u7063", "utc": 1529111407000, "level": 0, "avatar": "http://filestoresg1.beetalkmobile.com:8081/file/-7249017488094108281", "name": "\u771f\u5fc3\u518d\u4f86"}, "content": "\u52a0\u6cb9", "urls": [], "replies": {"first": [], "last": [], "noMoreReplies": true}, "images": [], "id": 90311138}, {"postBy": {"location": "\u53f0\u5317\u5e02\u00b7\u53f0\u7063", "utc": 1530348416000, "level": 0, "avatar": "http://filestoresg1.beetalkmobile.com:8081/file/2481753899363318845", "name": "\u5289\u9738\u9738"}, "content": "\u55ef~\u6216\u8a31\u59b3\u4e0d\u662f\u4ed6\u7684\u4eba\u9078\u5427\u2026\u2026", "urls": [], "replies": {"first": [], "last": [], "noMoreReplies": true}, "images": [], "id": 91327667}]}
