{"noMoreComments": true, "cursorEnd": 0, "id": "8823093", "comments": [{"postBy": {"location": "", "utc": 1529864544000, "level": 0, "avatar": "http://filestoresg1.beetalkmobile.com:8081/file/3624352088246650624", "name": "\u738b\u5bb8\u7def"}, "content": "\u6020\u901f\u96fb\u8166\u58de\u4e86", "urls": [], "replies": {"first": [], "last": [], "noMoreReplies": true}, "images": [], "id": 90941959}, {"postBy": {"location": "\u9ad8\u96c4\u5e02\u00b7\u53f0\u7063", "utc": 1529875750000, "level": 0, "avatar": "http://filestoresg1.beetalkmobile.com:8081/file/-1414296366483960902", "name": "Rex034"}, "content": "\u6aa2\u67e5\u706b\u661f\u585e\u63a5\u982d\u53cacdi\u5427", "urls": [], "replies": {"first": [], "last": [], "noMoreReplies": true}, "images": [], "id": 90947725}, {"postBy": {"location": "\u6843\u5712\u5e02\u00b7\u53f0\u7063", "utc": 1529894565000, "level": 0, "avatar": "http://filestoresg1.beetalkmobile.com:8081/file/-8438804518412722555", "name": "\u53eb\u6211\u5927\u53d4"}, "content": "\u6a13\u4e0a\u8aaa\u7684\u6020\u901f\u96fb\u8166\u6709\u554f\u984c<br />\u6216\u662f\u96fb\u7dda\u7dda\u8def\u6709\u554f\u984c\uff08\u77ed\u8def\uff09", "urls": [], "replies": {"first": [], "last": [], "noMoreReplies": true}, "images": [], "id": 90958692}, {"postBy": {"location": "\u9ad8\u96c4\u5e02\u00b7\u53f0\u7063", "utc": 1529904542000, "level": 0, "avatar": "http://filestoresg1.beetalkmobile.com:8081/file/7479315701995358801", "name": "\u7fd4\u4ed4"}, "content": "\u8b1d\u8b1d\u5404\u4f4d \u7d50\u679c\u662f\u706b\u661f\u585e\u84cb\u5b50\u6c27\u5316", "urls": [], "replies": {"first": [], "last": [], "noMoreReplies": true}, "images": [], "id": 90966858}, {"postBy": {"location": "\u65b0\u5317\u5e02\u00b7\u53f0\u7063", "utc": 1532370938000, "level": 0, "avatar": "http://filestoresg1.beetalkmobile.com:8081/file/6911657640258094217", "name": "\u55ae\u89aa\u7684\u8001\u7070\u9d28"}, "content": "\u6709\u53ef\u80fd\u542b\u6c27\u611f\u77e5\u5668\u9ad2\uff01<br />\u53bb\u6e05\u4e00\u6e05\u770b\u770b\uff01", "urls": [], "replies": {"first": [], "last": [], "noMoreReplies": true}, "images": [], "id": 92992567}, {"postBy": {"location": "\u53f0\u5357\u5e02\u00b7\u53f0\u7063", "utc": 1532388673000, "level": 0, "avatar": "http://filestoresg1.beetalkmobile.com:8081/file/-6930201991846365934", "name": "\u90b1\u5409\u723e\u7684\u90b1"}, "content": "\u6aa2\u67e5\u770b\u770b\u6020\u901f\u99ac\u9054\u6216\u662f\u7bc0\u6d41\u95a5\u9580\u6709\u7121\u78e8\u640d\u3002", "urls": [], "replies": {"first": [], "last": [], "noMoreReplies": true}, "images": [], "id": 93000999}, {"postBy": {"location": "\u9ad8\u96c4\u5e02\u00b7\u53f0\u7063", "utc": 1534617923000, "level": 0, "avatar": "http://filestoresg1.beetalkmobile.com:8081/file/-8836684785048308222", "name": "\u6e6f"}, "content": "\u50b3\u52d5\u662f\u63db\u65b0\u7684\u55ce\uff1f<br /><br />\u53ef\u80fd\u662f\u96e2\u5408\u5668\u5c0f\u5f48\u7c27\u6709\u65b7<br /><br />\u6211RSZ\u4e94\u671f\u5674\u5c04 \u6709\u767c\u751f\u904e<br /><br />\u75c7\u72c0\u8ddf\u4f60\u4e00\u6a23", "urls": [], "replies": {"first": [], "last": [], "noMoreReplies": true}, "images": [], "id": 94882068}, {"postBy": {"location": "\u65b0\u5317\u5e02\u00b7\u53f0\u7063", "utc": 1534619452000, "level": 0, "avatar": "http://filestoresg1.beetalkmobile.com:8081/file/-3837679289312465967", "name": "EDChang"}, "content": "\u67e5\u4e00\u67e5\u201c\u542b\u6c27\u611f\u77e5\u5668 \u201d", "urls": [], "replies": {"first": [], "last": [], "noMoreReplies": true}, "images": [], "id": 94883247}, {"postBy": {"location": "\u65b0\u5317\u5e02\u00b7\u53f0\u7063", "utc": 1534863239000, "level": 0, "avatar": "http://filestoresg1.beetalkmobile.com:8081/file/1408031295165723264", "name": "\u8a63\u54f2"}, "content": "\u96fb\u8166 \u5674\u6cb9\u5634 \u706b\u661f\u585e\u63a5\u982d \u9ad8\u58d3\u7dda\u5708\u90fd\u6709\u53ef\u80fd", "urls": [], "replies": {"first": [], "last": [], "noMoreReplies": true}, "images": [], "id": 95097264}]}
