{"noMoreComments": true, "cursorEnd": 0, "id": "8125339", "comments": [{"postBy": {"location": "\u53f0\u7063", "utc": 1522891673000, "level": 0, "avatar": "http://filestoresg1.beetalkmobile.com:8081/file/-7395862744292799834", "name": "\u7121\u76f8\u662f\u7a7a"}, "content": "\u59b3\u600e\u770b\u5230\u5fc3\u88e1\u6709\u4e00\u9053\u75a4\u75d5\u5462", "urls": [], "replies": {"first": [{"content": "\u53ef\u80fd\u5c0d\u8c61\u662f\u91ab\u751f", "reply": "", "id": 55051430, "name": "\u2744\u2744\ud83c\udf40\ud83c\udf40\ud83c\udf40\ud83c\udf40\ud83c\udf40"}, {"content": "@@\u2026\u9ed1\u5091\u514b\u4f86\u7684", "reply": "\u2744\u2744\ud83c\udf40\ud83c\udf40\ud83c\udf40\ud83c\udf40\ud83c\udf40", "id": 55051587, "name": "\u7121\u76f8\u662f\u7a7a"}], "last": [], "noMoreReplies": true}, "images": [], "id": 85247221}, {"postBy": {"location": "\u65b0\u5317\u5e02\u00b7\u53f0\u7063", "utc": 1522936827000, "level": 0, "avatar": "http://filestoresg1.beetalkmobile.com:8081/file/3624101377206096732", "name": "\ud83e\udd81ARMANI\ud83e\udd81"}, "content": "\u90a3\u4f60\u600e\u9ebc\u8655\u7406\u9019\u50b7\u75a4\u5462\uff1f", "urls": [], "replies": {"first": [], "last": [], "noMoreReplies": true}, "images": [], "id": 85293173}]}
