{"noMoreComments": true, "cursorEnd": 0, "id": "8377001", "comments": [{"postBy": {"location": "New Taipei City\u00b7Taiwan", "utc": 1525325930000, "level": 0, "avatar": "http://filestoresg1.beetalkmobile.com:8081/file/-5137983750272007356", "name": "T.h.Huang"}, "content": "\u5e0c\u671b\u5927\u5bb6\u90fd\u6c92\u4e8b\u2026\u2026<br />\ud83d\ude2e\ud83d\ude2e\ud83d\ude2e\ud83d\ude2e", "urls": [], "replies": {"first": [{"content": "\u5e73\u5b89\u5c31\u597d\uff0c:-D", "reply": "", "id": 55958068, "name": "chi*\u9ebb(Dama)"}], "last": [], "noMoreReplies": true}, "images": [], "id": 87303141}]}
