{"noMoreComments": true, "cursorEnd": 0, "id": "8746609", "comments": [{"postBy": {"location": "", "utc": 1529070778000, "level": 0, "avatar": "http://filestoresg1.beetalkmobile.com:8081/file/-426864496159914186", "name": "\u7c73\u6069"}, "content": "\u541b\u5982\ud83d\ude02", "urls": [], "replies": {"first": [{"content": "\u55e8\u55e8\u54c8\u54c8\u54c8", "reply": "", "id": 57239840, "name": "\u62b9\u62b9\u8336\ud83c\udf75"}, {"content": "\u7c97\u5976\u6c92\u591a\u4e45", "reply": "", "id": 57239940, "name": "\u62b9\u62b9\u8336\ud83c\udf75"}], "last": [], "noMoreReplies": true}, "images": [], "id": 90283077}]}
