{"noMoreComments": true, "cursorEnd": 0, "id": "8524188", "comments": [{"postBy": {"location": "\u9ad8\u96c4\u5e02\u00b7\u53f0\u7063", "utc": 1526754369000, "level": 0, "avatar": "http://filestoresg1.beetalkmobile.com:8081/file/7019079922517898344", "name": "\u273f\ud83c\udd71\ud83c\udd7e\ud83c\udd84\ud83c\udd81\ud83c\udd7d\ud83c\udd74\u273f"}, "content": "\u597d\u6587\u5fc5\u63a8\uff01", "urls": [], "replies": {"first": [{"content": "\u8b1d\u8b1d\u6367\u5834\ud83d\ude0f", "reply": "", "id": 56481336, "name": "\ud83d\udc3d\u5305\u5b50\ud83d\udc3d"}], "last": [{"content": "\u8b1d\u8b1d\u8001\u95c6", "reply": "\ud83d\udc3d\u5305\u5b50\ud83d\udc3d", "id": 56481352, "name": "\u273f\ud83c\udd71\ud83c\udd7e\ud83c\udd84\ud83c\udd81\ud83c\udd7d\ud83c\udd74\u273f"}, {"content": "\u8a18\u5f97\u7e73\u7248\u6b0a\u7a05\uff01", "reply": "\u273f\ud83c\udd71\ud83c\udd7e\ud83c\udd84\ud83c\udd81\ud83c\udd7d\ud83c\udd74\u273f", "id": 56481904, "name": "\ud83d\udc3d\u5305\u5b50\ud83d\udc3d"}], "noMoreReplies": true}, "images": [], "id": 88485882}, {"postBy": {"location": "\u9ad8\u96c4\u5e02\u00b7\u53f0\u7063", "utc": 1526793293000, "level": 0, "avatar": "http://filestoresg1.beetalkmobile.com:8081/file/6481047107241701880", "name": "\u6df1\u85cf..."}, "content": "\u975c\u5019\u8ab0\u5462\uff1f\u6211\u55ce\uff1f\ud83d\ude0d", "urls": [], "replies": {"first": [{"content": "\u4f60\u58de\u58de", "reply": "", "id": 56484961, "name": "\ud83d\udc3d\u5305\u5b50\ud83d\udc3d"}], "last": [], "noMoreReplies": true}, "images": [], "id": 88513547}]}
