{"noMoreComments": true, "cursorEnd": 0, "id": "8698083", "comments": [{"postBy": {"location": "\u53f0\u7063", "utc": 1528519320000, "level": 0, "avatar": "http://filestoresg1.beetalkmobile.com:8081/file/-3785974761945198415", "name": "\u54e9\u9001\u4e1f\u8cc0"}, "content": "\u600e\u9ebc\u611f\u89ba\u597d\u50cf\u6c34\u714e\u5305", "urls": [], "replies": {"first": [{"content": "\u65b0\u7af9\u597d\u591a\u5c0f\u7c60\u5305\u90fd\u9577\u7684\u50cf\u5305\u5b50 \ud83d\ude04\ud83d\ude04", "reply": "", "id": 57081504, "name": "AMBER"}, {"content": "\u771f\u5047@/@\u6709\u6642\u9593\u5728\u53bb\u5617\u9bae\u770b\u770b", "reply": "AMBER", "id": 57082354, "name": "\u54e9\u9001\u4e1f\u8cc0"}], "last": [], "noMoreReplies": true}, "images": [], "id": 89893301}, {"postBy": {"location": "\u65b0\u7af9\u7e23\u00b7\u53f0\u7063", "utc": 1536306153000, "level": 0, "avatar": "http://filestoresg1.beetalkmobile.com:8081/file/-4731582238767887869", "name": "Larry"}, "content": "\u597d\u5403\ud83d\ude0b", "urls": [], "replies": {"first": [], "last": [], "noMoreReplies": true}, "images": [], "id": 96285625}, {"postBy": {"location": "\u53f0\u5357\u5e02\u00b7\u53f0\u7063", "utc": 1536350693000, "level": 0, "avatar": "http://filestoresg1.beetalkmobile.com:8081/file/1429537748025461042", "name": "\u4e0d\u4ea4\u53cb\uff0c\u53ea\u770b\u6587"}, "content": "\u500b\u4eba\u53e3\u5473\u4e0d\u540c\uff0c\u6211\u559c\u6b61\u5403\u6b23\u5712", "urls": [], "replies": {"first": [{"content": "\u6b23\u5712\u5728\u54ea", "reply": "", "id": 59540151, "name": "AMBER"}], "last": [{"content": "\u6240\u4ee5\u6211\u8aaa\u6bcf\u500b\u4eba\u7684\u53e3\u5473\u4e0d\u540c\u554a\uff01\ud83d\ude0a\ud83d\ude0a", "reply": "AMBER", "id": 59603857, "name": "\u4e0d\u4ea4\u53cb\uff0c\u53ea\u770b\u6587"}, {"content": "\ud83d\udc4d\ud83d\udc4d\u8b1d\u8b1d\u4f60\u7684\u63a8\u85a6", "reply": "\u4e0d\u4ea4\u53cb\uff0c\u53ea\u770b\u6587", "id": 59606645, "name": "AMBER"}], "noMoreReplies": false}, "images": [], "id": 96328883}, {"postBy": {"location": "\u65b0\u5317\u5e02\u00b7\u53f0\u7063", "utc": 1536353385000, "level": 0, "avatar": "http://filestoresg1.beetalkmobile.com:8081/file/-2965337754935097679", "name": "\u65b9 \u8001\u5e2b"}, "content": "\u4e00\u65e9\u9192\u4f86\u5c31\u4f86\u901b\u98df\u7248<br /><br />\u5230\u5e95\u662f\u591a\u9913\u554a\u6211<br /><br />\u54c8\u54c8\u54c8", "urls": [], "replies": {"first": [], "last": [], "noMoreReplies": true}, "images": [], "id": 96330365}]}
