{"noMoreComments": true, "cursorEnd": 0, "id": "8276505", "comments": [{"postBy": {"location": "", "utc": 1524353326000, "level": 0, "avatar": "http://filestoresg1.beetalkmobile.com:8081/file/2", "name": "User blocked"}, "content": "   ", "urls": [], "replies": {"first": [{"content": "\u9019\u770b\u8d77\u4f86\u5f88\u4e0d\u8212\u670d \uff0c\u53ef\u4ee5\u522a\u55ce\uff1f", "reply": "", "id": 55601797, "name": "\u857e"}, {"content": "\u6240\u4ee5\u6211\u5c31\u8aaa\u672a\u6210\u5e74\u8acb\u52ff\u98f2\u9152", "reply": "\u857e", "id": 55602093, "name": "User blocked"}], "last": [], "noMoreReplies": true}, "images": ["http://filestoresg1.beetalkmobile.com:8081/file/eb0b5420660f8d538158923a90ddaa70"], "id": 86497183}, {"postBy": {"location": "\u53f0\u7063", "utc": 1524353554000, "level": 0, "avatar": "http://filestoresg1.beetalkmobile.com:8081/file/-7395862744292799834", "name": "\u7121\u76f8\u662f\u7a7a"}, "content": "\u4f86\uff01\u4ffa\u7d66\u59b3\u5237\u4e00\u5237\u3002\u5471\u5471", "urls": [], "replies": {"first": [{"content": "\u63db\u96bb\u9084\u884c\u7684\uff01", "reply": "", "id": 55601895, "name": "\u857e"}], "last": [{"content": "\u4ffa\u559c\u6b61\u5fa9\u53e4\u61f7\u820a\u6b3e\u5f0f\u7684\u2026\u5471\u5471", "reply": "\u857e", "id": 55602195, "name": "\u7121\u76f8\u662f\u7a7a"}, {"content": "\u958b\u5fc3\u5c31\u597d", "reply": "\u7121\u76f8\u662f\u7a7a", "id": 55640766, "name": "\u857e"}], "noMoreReplies": true}, "images": ["http://filestoresg1.beetalkmobile.com:8081/file/717dbdf630b9dcedc38e08727656d27e"], "id": 86497314}, {"postBy": {"location": "", "utc": 1524560474000, "level": 0, "avatar": "http://filestoresg1.beetalkmobile.com:8081/file/7381775840574504149", "name": "\u6211\u5c31\u662f\u8655\u5973\u5ea7"}, "content": "\u6709\u5fc3\u4e8b\u5537\u59d0", "urls": [], "replies": {"first": [{"content": "\u6c92\u6709^_^", "reply": "", "id": 55725623, "name": "\u857e"}], "last": [], "noMoreReplies": true}, "images": [], "id": 86686868}, {"postBy": {"location": "\u9ad8\u96c4\u5e02\u00b7\u53f0\u7063", "utc": 1524595644000, "level": 0, "avatar": "http://filestoresg1.beetalkmobile.com:8081/file/7100069971901177990", "name": "\u8d85\u65b0"}, "content": "\u4f60\u7684\u5b58\u5728\u611f\u8b93\u6211\u5bbf\u9189.......", "urls": [], "replies": {"first": [{"content": "\u5bbf\u9189\u5f88\u4e0d\u8212\u670d \u5410\u51fa\u4f86 \u5c31\u6703\u597d\u5f88\u591a\uff01", "reply": "", "id": 55725644, "name": "\u857e"}], "last": [{"content": "\u770b\u4f60\u5011\u5410\u7684\u90a3\u9ebc\u53b2\u5bb3 \uff0c\u6211\u8a72\u64bf\u8a0e\uff01\n\u5c24\u5176\u662f\u9023\u76ae\u5361\u4e18\u9019\u9ebc\u53ef\u611b\u7684\u5b8c\u610f\u5152\uff0c\u90fd\u5410\u7684\u9762\u76ee\u7319\u7370\u2026\u53ef\u6190\u6b38\uff5e\u54c8\u54c8\u54c8\u54c8\u3002", "reply": "\u8d85\u65b0", "id": 55762505, "name": "\u857e"}, {"content": "\ud83d\ude01\ud83d\ude01\ud83d\ude01", "reply": "\u857e", "id": 55767438, "name": "\u8d85\u65b0"}], "noMoreReplies": false}, "images": ["http://filestoresg1.beetalkmobile.com:8081/file/807386da588b1731550c12cd214aad68"], "id": 86726154}, {"postBy": {"location": "\u6843\u5712\u5e02\u00b7\u53f0\u7063", "utc": 1524601853000, "level": 0, "avatar": "http://filestoresg1.beetalkmobile.com:8081/file/7234690856962529986", "name": "\u81ea\u7531\u7684\u6d77\u8c5a"}, "content": "\u3124\u3124", "urls": [], "replies": {"first": [{"content": "\u665a\u3124\u3124", "reply": "", "id": 55725676, "name": "\u857e"}], "last": [], "noMoreReplies": true}, "images": [], "id": 86729709}, {"postBy": {"location": "\u53f0\u5357\u5e02\u00b7\u53f0\u7063", "utc": 1524709981000, "level": 0, "avatar": "http://filestoresg1.beetalkmobile.com:8081/file/-216702742495545771", "name": "\u5091"}, "content": "\u65e9\u5b89", "urls": [], "replies": {"first": [{"content": "\u665a\u5b89 \u5091\uff01", "reply": "", "id": 55762521, "name": "\u857e"}], "last": [], "noMoreReplies": true}, "images": [], "id": 86814884}, {"postBy": {"location": "\u9ad8\u96c4\u5e02\u00b7\u53f0\u7063", "utc": 1525010077000, "level": 0, "avatar": "http://filestoresg1.beetalkmobile.com:8081/file/3565624973876991367", "name": "\u963f\u5409  \u8272\u60c5\u52ff\u64fe\u5594"}, "content": "@@\u4ed6\u5011\u9019\u6a23\u9084\u771f\u6c92\u79ae\u8c8c\u3002 \u4f60\u597d\u963f", "urls": [], "replies": {"first": [{"content": "\u963f\u5409 \u6c92\u95dc\u4fc2\u5566\uff01\u770b\u5728\u4ed6\u5011\u6709\u6642\u5019\u201c\u9178\u7684\u6709\u7406\u201d\u7684\u4efd\u4e0a\uff0c\u59d0\u4e00\u7b11\u7f6e\u4e4b\uff5e\u7121\u50b7\u5927\u96c5^_^", "reply": "", "id": 55886263, "name": "\u857e"}], "last": [], "noMoreReplies": true}, "images": [], "id": 87056524}, {"postBy": {"location": "\u53f0\u7063", "utc": 1525040244000, "level": 0, "avatar": "http://filestoresg1.beetalkmobile.com:8081/file/6372018452316629555", "name": "\u9ec3\u5c0f\u5cfb"}, "content": "\u59d0\u59d0\u65e9\u5b89", "urls": [], "replies": {"first": [{"content": "\u5c0f\u5cfb \u665a\u5b89\uff01", "reply": "", "id": 55886311, "name": "\u857e"}], "last": [], "noMoreReplies": true}, "images": [], "id": 87080436}, {"postBy": {"location": "\u65b0\u5317\u5e02\u00b7\u53f0\u7063", "utc": 1525181641000, "level": 0, "avatar": "http://filestoresg1.beetalkmobile.com:8081/file/-3096191740136954139", "name": "\u5433\u535a\u921e"}, "content": "\u53ef\u4ee5\u3002\u5c31\u4f86\u804a\u804a", "urls": [], "replies": {"first": [{"content": "\u591c\u6df1\u4e86\uff01\u665a\u5b89 \u597d\u5922\uff5e", "reply": "", "id": 55946252, "name": "\u857e"}], "last": [], "noMoreReplies": true}, "images": [], "id": 87191286}, {"postBy": {"location": "\u53f0\u4e2d\u5e02\u00b7\u53f0\u7063", "utc": 1525265952000, "level": 0, "avatar": "http://filestoresg1.beetalkmobile.com:8081/file/85703655590909085", "name": "\u55ae\u7d14\u8207\u7f8e\u597d"}, "content": "  ", "urls": [], "replies": {"first": [{"content": "\u54c8\u54c8\u54c8\u54c8\u2026\u4f60\u5f88\u662f\u4e86\u89e3\u6211^_^", "reply": "", "id": 55946235, "name": "\u857e"}, {"content": "\u6211\u770b\u7a7f\u59b3\u4e86\u55ce\uff0c\u54c8\u54c8\u54c8", "reply": "\u857e", "id": 55948567, "name": "\u55ae\u7d14\u8207\u7f8e\u597d"}], "last": [], "noMoreReplies": true}, "images": ["http://filestoresg1.beetalkmobile.com:8081/file/5c7b2a701c01b43c73129b4346d05fb6"], "id": 87257478}, {"postBy": {"location": "\u53f0\u4e2d\u5e02\u00b7\u53f0\u7063", "utc": 1525574003000, "level": 0, "avatar": "http://filestoresg1.beetalkmobile.com:8081/file/8016870255453873450", "name": "\u5c0f\u767d\ud83d\udc37"}, "content": "\u59b9\u59b9\u597d", "urls": [], "replies": {"first": [], "last": [], "noMoreReplies": true}, "images": [], "id": 87496550}, {"postBy": {"location": "\u9ad8\u96c4\u5e02\u00b7\u53f0\u7063", "utc": 1525674028000, "level": 0, "avatar": "http://filestoresg1.beetalkmobile.com:8081/file/-6305917984346442017", "name": "\u5f71\u5b50"}, "content": "\u59d1\u5a18\u59b3\u597d\u5440\uff01\u52a0\u6cb9\u5594\uff01", "urls": [], "replies": {"first": [], "last": [], "noMoreReplies": true}, "images": [], "id": 87576812}, {"postBy": {"location": "\u65b0\u7af9\u7e23\u00b7\u53f0\u7063", "utc": 1525740965000, "level": 0, "avatar": "http://filestoresg1.beetalkmobile.com:8081/file/-2686756716812046065", "name": "\u5e73\u5e73\u6de1\u6de1\u7c21\u7c21\u55ae\u55ae"}, "content": "\u5e6b\u59b3\u9ede\ud83d\udc4d\u9583\u4eba\ud83d\udc4d\ud83d\udc4d", "urls": [], "replies": {"first": [], "last": [], "noMoreReplies": true}, "images": [], "id": 87629458}]}
