{"noMoreComments": true, "cursorEnd": 0, "id": "8220564", "comments": [{"postBy": {"location": "\u6843\u5712\u5e02\u00b7\u53f0\u7063", "utc": 1523994416000, "level": 0, "avatar": "http://filestoresg1.beetalkmobile.com:8081/file/930548126075295862", "name": "Sam \u0e40\u0e01\u0e48\u0e32"}, "content": "\u5176\u5be6\u4e0b\u8e4b\u98ef\u5e97\u6709\u6642\u5c31\u6709\uff0c\u4e0d\u7136\u53bb\u5927\u8ce3\u5834\u901b\u6709\u9732\u5929\u7684\u4e5f\u6709\u5e97\u9762\u8f03\u5b89\u5168", "urls": [], "replies": {"first": [{"content": "\u4e86\u89e3  \u8b1d\u8b1d\u4f60\u5594", "reply": "", "id": 55453768, "name": "\u8fb0chin"}], "last": [], "noMoreReplies": true}, "images": [], "id": 86180725}, {"postBy": {"location": "Chang Wat Phra Nakhon Si Ayutthaya\u00b7\u6cf0\u570b", "utc": 1524095802000, "level": 0, "avatar": "http://filestoresg1.beetalkmobile.com:8081/file/-3321977546512417018", "name": "Tank\u6cf0\u570b\ud83c\uddf9\ud83c\udded\u5df4\u771f\u4e73\u81a0\u6795\u4ee3\u7406\u0e2a\u0e27\u0e31\u0e2a\u0e14\u0e35"}, "content": "\u4f60\u81ea\u5df1\u559c\u6b61\u9ad8\u6a94\u9084\u662f\u4e00\u822c..Asok\u6709Health land", "urls": [], "replies": {"first": [{"content": "\u90fd\u60f3\u8a66\u8a66\u770b!!!\n\u50cf \u963f\u7d22\u514b\u7684 Health land \u9019\u7a2e\u9ad8\u6a94\u7684\u5e97  \u8981\u9810\u7d04\u55ce\uff1f", "reply": "", "id": 55490001, "name": "\u8fb0chin"}, {"content": "\u4e0a kk day \u8cb7\u7968\u5238 \u6709\u512a\u60e0", "reply": "", "id": 55660800, "name": "\u767d\u5c0f\u82b1"}], "last": [], "noMoreReplies": true}, "images": [], "id": 86264105}, {"postBy": {"location": "\u53f0\u5317\u5e02\u00b7\u53f0\u7063", "utc": 1524501530000, "level": 0, "avatar": "http://filestoresg1.beetalkmobile.com:8081/file/-5984728639939319872", "name": "\u5bc2\u5bde\u7684\u59ae"}, "content": "\u4f60\u5e7e\u865f\u53bb\uff1f\u62110519\u53bb\u5341\u5929\uff0c\u4e5f\u60f3\u627e\u5973\u5b50spa  \u6309\u6469", "urls": [], "replies": {"first": [{"content": "5/17\u51fa\u767c  ", "reply": "", "id": 55699864, "name": "\u8fb0chin"}, {"content": "\u5230\u6642\u5019\u6709\u65b0\u767c\u73fe\u8a18\u5f97\u4ea4\u6d41\u4e00\u4e0b", "reply": "", "id": 55753441, "name": "\u5bc2\u5bde\u7684\u59ae"}], "last": [], "noMoreReplies": true}, "images": [], "id": 86639896}, {"postBy": {"location": "\u6843\u5712\u5e02\u00b7\u53f0\u7063", "utc": 1524530682000, "level": 0, "avatar": "http://filestoresg1.beetalkmobile.com:8081/file/930548126075295862", "name": "Sam \u0e40\u0e01\u0e48\u0e32"}, "content": "\u5176\u5be6\u4e0b\u65b0\u6a5f\u5834\u9644\u8fd1IKEA\u5546\u5834\u4e8c\u6a13\u5c31\u6709\u6cf0\u5f0f\u6309\u6469\u4e5f\u6709Sap\u5973\u6027\u670d\u52d9\u9760\u8fd1\u5927\u7684\u5927C \u9019\u908a\u8ce3\u5834\u6709\u5c0e\u904a\u5716\u6309\u6469\u5e97\u6709\u4e2d\u6587\u5c0d\u9762Sap \u5e97\uff0c\u4e00\u6a13\u516c\u8eca\u8f49\u904b\u7ad9", "urls": [], "replies": {"first": [{"content": "\u5927C. \u6211\u4e5f\u6703\u53bb\u901b  \u53ef\u4ee5\u770b\u770b\u5594  \u8b1d\u8b1d\u4f60\u5594", "reply": "", "id": 55699833, "name": "\u8fb0chin"}, {"content": "\u53bb\u53ef\u8cb7\u884c\u7a0b\u53bb\u7f85\u52c7\u5403\u6c34\u679c\u5403\u5230\u98fd\uff0c\u4e00\u65e5\u5377\u624d350\u9296", "reply": "", "id": 57032528, "name": "Sam \u0e40\u0e01\u0e48\u0e32"}], "last": [], "noMoreReplies": true}, "images": [], "id": 86659064}]}
